{
  "results": [
    {
      "name": "iPhone 6",
      "color": 8,
      "email": "mailto:fikregeorgies@gmail.com?subject=I wan't to buy\u0026body=Hey I wan't to buy",
      "image": "https://pbs.twimg.com/media/FBGHMlCXEAAmZqH?format=jpg&name=small",
      "image1": "https://pbs.twimg.com/media/FBGHMlAWEAAnm6w?format=jpg&name=small",
      "image2": "https://pbs.twimg.com/media/FBGHMk8WUAQ4oKo?format=jpg&name=small",
      "image3": "",
      "image4": "",
      "phone": "tel://+251941681510",
      "price": "4500",
      "title": "n01",
      "color1": 4,
      "color2": 7,
      "descri": "Slightly used iPhone 6, good condition, \n Released 2014, September 19\n 129g, 6.9mm thickness\n iOS 8, up to iOS 12.4.6\n 16GB",
      "phone1": "tel://+251904356731",
      "watsapp": "https://wa.me/${251941681510}?text=Hey i Wan't to Sell ",
      "delivery": "Free delivery",
      "location": "Bahir Dar",
      "telegram": "https://t.me/fmansuperfly?text=Hey i Wan't to buy ",
      "condition": "Slightly Used!"
    },
    {
      "name": "Tecno W4",
      "color": 8,
      "email": "mailto:fikregeorgies@gmail.com?subject=I wan't to buy\u0026body=Hey I wan't to buy",
      "image": "https://pbs.twimg.com/media/FBGHPfvXsAAHFUq?format=jpg&name=small",
      "image1": "https://pbs.twimg.com/media/FBGHPe1XoAgWH2O?format=jpg&name=small",
      "image2": "https://pbs.twimg.com/media/FBGHPeKX0Ak1bnl?format=jpg&name=small",
      "image3": "",
      "image4": "",
      "phone": "tel://+251941681510",
      "price": "2500",
      "title": "n02",
      "color1": 4,
      "color2": 7,
      "descri": "Slightly used Tecno W4, good condition,\n Sim card type: Micro-SIM\n Communication: WLAN, Bluetooth, 3G, 2G\n Camera: 8.0 megapixel\n Display: 4.5'\n Memory: 8.0 Gb, 1.0 Gb, 32 Gb microSD card (microSD) ",
      "phone1": "tel://+251904356731",
      "watsapp": "https://wa.me/${251941681510}?text=Hey i Wan't to Sell ",
      "delivery": "Free delivery",
      "location": "Bahir Dar",
      "telegram": "https://t.me/fmansuperfly?text=Hey i Wan't to buy ",
      "condition": "Used"
    },
    {
      "name": "Samsung Galaxy A12",
      "color": 8,
      "email": "mailto:fikregeorgies@gmail.com?subject=I wan't to buy\u0026body=Hey I wan't to buy",
      "image": "https://fdn2.gsmarena.com/vv/bigpic/samsung-galaxy-a12-nacho.jpg",
      "image1": "",
      "image2": "",
      "image3": "",
      "image4": "",
      "phone": "tel://+251941681510",
      "price": "10500",
      "title": "n03",
      "color1": 4,
      "color2": 7,
      "descri": "Brand new Samsung Galaxy A12, \n 205g, 8.9mm thickness, \n Android 11,\n One UI 3.132GB/64GB/128GB storage, microSDXC",
      "phone1": "tel://+251904356731",
      "watsapp": "https://wa.me/${251941681510}?text=Hey i Wan't to Sell ",
      "delivery": "Free delivery",
      "location": "Bahir Dar",
      "telegram": "https://t.me/fmansuperfly?text=Hey i Wan't to buy ",
      "condition": "New"
    },
    {
      "name": "Samsung Galaxy M11",
      "color": 8,
      "email": "mailto:fikregeorgies@gmail.com?subject=I wan't to buy\u0026body=Hey I wan't to buy",
      "image": "https://fdn2.gsmarena.com/vv/bigpic/samsung-galaxy-m11-sm-m115.jpg",
      "image1": "",
      "image2": "",
      "image3": "",
      "image4": "",
      "phone": "tel://+251941681510",
      "price": "10500",
      "title": "n04",
      "color1": 4,
      "color2": 7,
      "descri": "Brand new Samsung Galaxy M11, Released 2020, May 4\n 197g, 9mm thickness \nAndroid 10, up to Android 11, One UI 3.1 \n32GB/64GB storage, microSDXC",
      "phone1": "tel://+251904356731",
      "watsapp": "https://wa.me/${251941681510}?text=Hey i Wan't to Sell ",
      "delivery": "Free delivery",
      "location": "Bahir Dar",
      "telegram": "https://t.me/fmansuperfly?text=Hey i Wan't to buy ",
      "condition": "New"
    },
    {
      "name": "Samsung Galaxy M02",
      "color": 8,
      "email": "mailto:fikregeorgies@gmail.com?subject=I wan't to buy\u0026body=Hey I wan't to buy",
      "image": "https://fdn2.gsmarena.com/vv/bigpic/samsung-galaxy-m02.jpg",
      "image1": "",
      "image2": "",
      "image3": "",
      "image4": "",
      "phone": "tel://+251941681510",
      "price": "8000",
      "title": "n05",
      "color1": 4,
      "color2": 7,
      "descri": "Brand new Samsung Galaxy M02, \n \n Released 2021, February 09\n thikness: 206g, 9.1mm thickness\n Android 10, One UI 2.0\n 32GB storage, microSDXC\n pixel 6.5'7201600 pixels\n 13MP\n 3GB RAM",
      "phone1": "tel://+251904356731",
      "watsapp": "https://wa.me/${251941681510}?text=Hey i Wan't to Sell ",
      "delivery": "Free delivery",
      "location": "Bahir Dar",
      "telegram": "https://t.me/fmansuperfly?text=Hey i Wan't to buy ",
      "condition": "New"
    },
    {
      "name": "Samsung Galaxy A10s",
      "color": 8,
      "email": "mailto:fikregeorgies@gmail.com?subject=I wan't to buy\u0026body=Hey I wan't to buy",
      "image": "https://fdn2.gsmarena.com/vv/bigpic/samsung-galaxy-a12-nacho.jpg",
      "image1": "",
      "image2": "",
      "image3": "",
      "image4": "",
      "phone": "tel://+251941681510",
      "price": "8500",
      "title": "n06",
      "color1": 4,
      "color2": 7,
      "descri": "Brand new Samsung Galaxy A10s, \n \n Released 2019, August 27\n 168g, 7.8mm thickness\n Android 9.0, up to Android 11, One UI 3.1\n 32GB storage, microSDXC",
      "phone1": "tel://+251904356731",
      "watsapp": "https://wa.me/${251941681510}?text=Hey i Wan't to Sell ",
      "delivery": "Free delivery",
      "location": "Bahir Dar",
      "telegram": "https://t.me/fmansuperfly?text=Hey i Wan't to buy ",
      "condition": "New"
    },
    {
      "name": "Tecno Spark 7",
      "color": 8,
      "email": "mailto:fikregeorgies@gmail.com?subject=I wan't to buy\u0026body=Hey I wan't to buy",
      "image": "https://fdn2.gsmarena.com/vv/bigpic/tecno-spark-7.jpg",
      "image1": "",
      "image2": "",
      "image3": "",
      "image4": "",
      "phone": "tel://+251941681510",
      "price": "8500",
      "title": "n07",
      "color1": 4,
      "color2": 7,
      "descri": "Brand new Tecno Spark 7, \n \n Released 2021, April 16\n 9.5mm thickness\n Android 11, HIOS 7.5\n 32GB/64GB storage, microSDXC",
      "phone1": "tel://+251904356731",
      "watsapp": "https://wa.me/${251941681510}?text=Hey i Wan't to Sell ",
      "delivery": "Free delivery",
      "location": "Bahir Dar",
      "telegram": "https://t.me/fmansuperfly?text=Hey i Wan't to buy ",
      "condition": "New"
    },
    {
      "name": "Tecno Spark Go 2021",
      "color": 8,
      "email": "mailto:fikregeorgies@gmail.com?subject=I wan't to buy\u0026body=Hey I wan't to buy",
      "image": "https://fdn2.gsmarena.com/vv/bigpic/samsung-galaxy-a12-nacho.jpg",
      "image1": "",
      "image2": "",
      "image3": "",
      "image4": "",
      "phone": "tel://+251941681510",
      "price": "7000",
      "title": "n08",
      "color1": 4,
      "color2": 7,
      "descri": "Brand new Tecno Spark Go 2021,\n Released 2021, July 07\n 193g, 9.1mm thickness\n Android 10, HiOS 6.2\n 32GB storage, microSDXC",
      "phone1": "tel://+251904356731",
      "watsapp": "https://wa.me/${251941681510}?text=Hey i Wan't to Sell ",
      "delivery": "Free delivery",
      "location": "Bahir Dar",
      "telegram": "https://t.me/fmansuperfly?text=Hey i Wan't to buy ",
      "condition": "New"
    }

  ]
}
